strategy_analysis/__init__.py
strategy_analysis/dpd.py
strategy_analysis/getdata.py
strategy_analysis/migrations.py
strategy_analysis/prefilters.py
strategy_analysis/util.py
johnshopeetools-0.1.18.dist-info/METADATA
johnshopeetools-0.1.18.dist-info/WHEEL
johnshopeetools-0.1.18.dist-info/top_level.txt
johnshopeetools-0.1.18.dist-info/RECORD
