Metadata-Version: 2.1
Name: johnshopeetools
Version: 0.1.18
Summary: A toolbox for credit policy analysis
Home-page: UNKNOWN
Author: John Chan | making difficult live easier
Author-email: john.chanky@seamoney.com
License: UNKNOWN
Platform: UNKNOWN
Requires-Dist: pandas
Requires-Dist: pyhive
